.clang-format
.gitignore
CMakeLists.txt
LICENSE
README.md
pyproject.toml
setup.cfg
setup.py
.github/workflows/ci_cd.yml
.github/workflows/style.yml
plugins/actuation_delay/ActuationDelay.cpp
plugins/actuation_delay/ActuationDelay.h
plugins/actuation_delay/CMakeLists.txt
plugins/actuation_delay/README.md
plugins/low_pass_target/CMakeLists.txt
plugins/low_pass_target/LowPassTarget.cpp
plugins/low_pass_target/LowPassTarget.h
plugins/low_pass_target/README.md
python/gazebo_scenario_plugins/__init__.py
python/gazebo_scenario_plugins/plugin.py
python/gazebo_scenario_plugins/plugins.py
python/gazebo_scenario_plugins.egg-info/PKG-INFO
python/gazebo_scenario_plugins.egg-info/SOURCES.txt
python/gazebo_scenario_plugins.egg-info/dependency_links.txt
python/gazebo_scenario_plugins.egg-info/not-zip-safe
python/gazebo_scenario_plugins.egg-info/requires.txt
python/gazebo_scenario_plugins.egg-info/top_level.txt
tests/test_actuation_delay.py