Metadata-Version: 2.1
Name: gazebo-scenario-plugins
Version: 0.2.1.dev3
Summary: Plugins for the Ignition Gazebo simulator implemented with ScenarIO.
Home-page: https://github.com/ami-iit/gazebo-scenario-plugins
Author: Diego Ferigo
Author-email: dgferigo@gmail.com
License: LGPL
Project-URL: Changelog, https://github.com/ami-iit/gazebo-scenario-plugins/releases
Project-URL: Tracker, https://github.com/ami-iit/gazebo-scenario-plugins/issues
Project-URL: Source, https://github.com/ami-iit/gazebo-scenario-plugins
Keywords: gazebo,ignition,simulation,robotics,plugin
Platform: linux
Classifier: Development Status :: 4 - Beta
Classifier: Operating System :: POSIX :: Linux
Classifier: Topic :: Games/Entertainment :: Simulation
Classifier: Topic :: Scientific/Engineering :: Physics
Classifier: Framework :: Robot Framework
Classifier: Intended Audience :: Developers
Classifier: Intended Audience :: Science/Research
Classifier: Programming Language :: C++
Classifier: Programming Language :: Python :: 3
Classifier: Programming Language :: Python :: 3 :: Only
Classifier: Programming Language :: Python :: 3.8
Classifier: Programming Language :: Python :: 3.9
Classifier: Programming Language :: Python :: Implementation :: CPython
Classifier: License :: OSI Approved :: GNU Lesser General Public License v2 or later (LGPLv2+)
Requires-Python: >=3.8
Provides-Extra: test
Provides-Extra: all
License-File: LICENSE
